Metadata-Version: 2.1
Name: odoo8-addon-website-portal-sale
Version: 8.0.1.0.0.99.dev39
Summary: Add your sales document in the frontend portal (sales order, quotations, invoices)
Home-page: https://www.odoo.com/, http://www.wearemonk.com, http://www.antiun.com
Author: Odoo SA, MONK Software, Antiun Ingenieria S.L., Odoo Community Association (OCA)
Author-email: support@odoo-community.org
License: LGPL-3
Platform: UNKNOWN
Classifier: Programming Language :: Python
Classifier: Framework :: Odoo
Classifier: Framework :: Odoo :: 8.0
Classifier: License :: OSI Approved :: GNU Lesser General Public License v3 (LGPLv3)
Requires-Python: ~=2.7
Requires-Dist: odoo8-addon-website-portal
Requires-Dist: odoo (<9.0a,>=8.0a)
